computer_control_mcp/FZYTK.TTF
computer_control_mcp/__init__.py
computer_control_mcp/__main__.py
computer_control_mcp/cli.py
computer_control_mcp/core.py
computer_control_mcp/gui.py
computer_control_mcp/server.py
computer_control_mcp/test.py
computer_control_mcp/test_image.png
computer_control_mcp-0.3.9.dist-info/METADATA
computer_control_mcp-0.3.9.dist-info/WHEEL
computer_control_mcp-0.3.9.dist-info/entry_points.txt
computer_control_mcp-0.3.9.dist-info/licenses/LICENSE
computer_control_mcp-0.3.9.dist-info/RECORD
