Metadata-Version: 2.4
Name: computer-control-mcp
Version: 0.3.9
Summary: MCP server that provides computer control capabilities, like mouse, keyboard, OCR, etc. using PyAutoGUI, RapidOCR, ONNXRuntime. Similar to 'computer-use' by Anthropic. With Zero External Dependencies.
Project-URL: Homepage, https://github.com/AB498/computer-control-mcp
Project-URL: Issues, https://github.com/AB498/computer-control-mcp/issues
Project-URL: Documentation, https://github.com/AB498/computer-control-mcp#readme
Author-email: AB498 <abcd49800@gmail.com>
License: MIT
License-File: LICENSE
Classifier: Development Status :: 4 - Beta
Classifier: Intended Audience :: Developers
Classifier: License :: OSI Approved :: MIT License
Classifier: Programming Language :: Python :: 3
Classifier: Programming Language :: Python :: 3.12
Classifier: Topic :: Software Development :: Libraries
Classifier: Topic :: Utilities
Requires-Python: >=3.8
Requires-Dist: fuzzywuzzy==0.18.0
Requires-Dist: mcp[cli]==1.13.0
Requires-Dist: mss>=7.0.0
Requires-Dist: onnxruntime==1.22.0
Requires-Dist: opencv-python==4.12.0.88
Requires-Dist: pillow==11.3.0
Requires-Dist: pyautogui==0.9.54
Requires-Dist: pygetwindow==0.0.9
Requires-Dist: python-levenshtein>=0.20.9
Requires-Dist: pywinctl==0.4.1
Requires-Dist: rapidocr-onnxruntime==1.2.3
Requires-Dist: rapidocr==3.3.1
Requires-Dist: windows-capture>=1.0.0; sys_platform == 'win32'
